nsq/__init__.py
nsq/command.py
nsq/compat.py
nsq/connection.py
nsq/connection_callbacks.py
nsq/connection_election.py
nsq/constants.py
nsq/consumer.py
nsq/exceptions.py
nsq/identify.py
nsq/lookup.py
nsq/master.py
nsq/message_handler.py
nsq/node.py
nsq/node_collection.py
nsq/producer.py
nsq/server.py
nsq/config/__init__.py
nsq/config/client.py
nsq/config/handle.py
nsq/config/lookup.py
nsq/config/protocol.py
nsq/resources/README.rst
nsq/resources/requirements.txt
nsqs-0.2.0.dist-info/DESCRIPTION.rst
nsqs-0.2.0.dist-info/METADATA
nsqs-0.2.0.dist-info/metadata.json
nsqs-0.2.0.dist-info/RECORD
nsqs-0.2.0.dist-info/top_level.txt
nsqs-0.2.0.dist-info/WHEEL
