Metadata-Version: 2.0
Name: nsqs
Version: 0.2.0
Summary: A complete, gevent-based, non-Tornado NSQ client.
Home-page: https://github.com/dsoprea/NsqSpinner
Author: Dustin Oprea
Author-email: myselfasunder@gmail.com
License: GPL 2
Platform: UNKNOWN
